py_xbrl-2.2.17.dist-info/licenses/LICENSE
xbrl/__init__.py
xbrl/cache.py
xbrl/instance.py
xbrl/linkbase.py
xbrl/taxonomy.py
xbrl/helper/__init__.py
xbrl/helper/connection_manager.py
xbrl/helper/text2num.py
xbrl/helper/uri_helper.py
xbrl/helper/xml_parser.py
xbrl/transformations/__init__.py
xbrl/transformations/text2num.py
py_xbrl-2.2.17.dist-info/METADATA
py_xbrl-2.2.17.dist-info/WHEEL
py_xbrl-2.2.17.dist-info/top_level.txt
py_xbrl-2.2.17.dist-info/RECORD
