Metadata-Version: 2.4
Name: py-xbrl
Version: 2.2.17
Summary: Parser for parsing XBRL and iXBRL files (instance documents, taxonomy schemas, taxonomy linkbases).
Home-page: https://github.com/manusimidt/xbrl_parser
Author: Manuel Schmidt
Author-email: hello@schmidt-manuel.de
License: GNU General Public License v3 (GPLv3)
Classifier: Development Status :: 5 - Production/Stable
Classifier: Programming Language :: Python :: 3.9
Classifier: Programming Language :: Python :: 3.10
Classifier: Programming Language :: Python :: 3.11
Classifier: Programming Language :: Python :: 3.12
Classifier: Programming Language :: Python :: 3.13
Classifier: Programming Language :: Python :: 3.14
Classifier: Natural Language :: English
Classifier: Topic :: Office/Business :: Financial :: Accounting
Classifier: Topic :: Office/Business :: Financial :: Investment
Classifier: Topic :: Text Processing :: Markup :: XML
License-File: LICENSE
Requires-Dist: requests
Requires-Dist: urllib3
Dynamic: author
Dynamic: author-email
Dynamic: classifier
Dynamic: description
Dynamic: description-content-type
Dynamic: home-page
Dynamic: license
Dynamic: license-file
Dynamic: requires-dist
Dynamic: summary
